lznlp/__init__.py
lznlp/client.py
lznlp/exceptions.py
lznlp/labeling.py
lznlp/rabbit.py
lznlp-0.1.4.dist-info/METADATA
lznlp-0.1.4.dist-info/WHEEL
lznlp-0.1.4.dist-info/top_level.txt
lznlp-_.dist-info/METADATA
lznlp-_.dist-info/WHEEL
lznlp-_.dist-info/top_level.txt
lznlp-0.1.4.dist-info/RECORD
