Metadata-Version: 2.1
Name: lznlp
Version: 0.1.4
Summary: LiangZhiNLP API wrapper
Home-page: http://192.168.1.26:8099/liangzhi.ai/lznlp-platform/tree/master/scripts/lznlp.sdk
Author: liangzhi
Author-email: service@quant-chi.com
License: MIT
Platform: UNKNOWN
Classifier: Development Status :: 5 - Production/Stable
Classifier: Intended Audience :: Developers
Classifier: Operating System :: OS Independent
Classifier: Programming Language :: Python :: 3
Classifier: License :: OSI Approved :: MIT License
Classifier: Topic :: Software Development :: Libraries :: Python Modules
Classifier: Topic :: Software Development :: Testing
Requires-Dist: requests (>=2.0.0)
Requires-Dist: nose
Requires-Dist: keras
Requires-Dist: xgboost
Requires-Dist: pika
Requires-Dist: scrapy
Requires-Dist: w3lib
Requires-Dist: lxml
